{
	"configurations" : 
	[
		{
			"directories" : 
			[
				{
					"build" : ".",
					"jsonFile" : "directory-.-Debug-d0094a50bb2071803777.json",
					"minimumCMakeVersion" : 
					{
						"string" : "3.6.0"
					},
					"projectIndex" : 0,
					"source" : ".",
					"targetIndexes" : 
					[
						0
					]
				}
			],
			"name" : "Debug",
			"projects" : 
			[
				{
					"directoryIndexes" : 
					[
						0
					],
					"name" : "detection_based_tracker",
					"targetIndexes" : 
					[
						0
					]
				}
			],
			"targets" : 
			[
				{
					"directoryIndex" : 0,
					"id" : "detection_based_tracker::@6890427a1f51a3e7e1df",
					"jsonFile" : "target-detection_based_tracker-Debug-f27e75949f36b88c5da8.json",
					"name" : "detection_based_tracker",
					"projectIndex" : 0
				}
			]
		}
	],
	"kind" : "codemodel",
	"paths" : 
	{
		"build" : "C:/Users/DELL/Downloads/OpenCV-4.7.0/samples/face-detection/.cxx/Debug/5n6z5c3d/arm64-v8a",
		"source" : "C:/Users/DELL/Downloads/OpenCV-4.7.0/samples/face-detection/jni"
	},
	"version" : 
	{
		"major" : 2,
		"minor" : 3
	}
}
